acore_server_config/__init__.py
acore_server_config/_version.py
acore_server_config/api.py
acore_server_config/boto_ses.py
acore_server_config/compat.py
acore_server_config/in_ec2.py
acore_server_config/paths.py
acore_server_config/runtime.py
acore_server_config/config/__init__.py
acore_server_config/config/init.py
acore_server_config/config/loader.py
acore_server_config/config/define/__init__.py
acore_server_config/config/define/main.py
acore_server_config/config/define/server.py
acore_server_config/docs/__init__.py
acore_server_config/tests/__init__.py
acore_server_config/tests/dummy_config.py
acore_server_config/tests/helper.py
acore_server_config/tests/mock_aws.py
acore_server_config/vendor/__init__.py
acore_server_config/vendor/pytest_cov_helper.py
acore_server_config-0.6.3.dist-info/AUTHORS.rst
acore_server_config-0.6.3.dist-info/LICENSE.txt
acore_server_config-0.6.3.dist-info/METADATA
acore_server_config-0.6.3.dist-info/WHEEL
acore_server_config-0.6.3.dist-info/top_level.txt
acore_server_config-0.6.3.dist-info/RECORD
